.gitignore
LICENSE.txt
Particle Viewer.ipynb
README.md
example.zoom
setup.cfg
setup.py
zoomin
zoomin_collect_particles
scripts/submit_enzo_job.sb
scripts/submit_music_job.sb
scripts/submit_particle_job.sb
src/__init__.py
src/Zoomer/__init__.py
src/Zoomer/collect_halo_particles.py
src/Zoomer/load_halo_catalog.py
src/Zoomer/run.py
src/Zoomer/show_particles.py
src/Zoomer/unit_tests.py
src/Zoomer/validateConfig.py
src/Zoomer/write_enzo_config.py
src/Zoomer/write_level_config.py
src/Zoomer/write_music_config.py
src/Zoomer/zoom.py
src/Zoomin.egg-info/PKG-INFO
src/Zoomin.egg-info/SOURCES.txt
src/Zoomin.egg-info/dependency_links.txt
src/Zoomin.egg-info/requires.txt
src/Zoomin.egg-info/top_level.txt
tests/CloudyData_UVB=HM2012_shielded.h5
tests/MUSIC_base.conf
tests/enzo_base.enzo
tests/halo_catalog.ascii
tests/wmap9_transfer_function_z99.dat
tests/solutions/Test_L0/ParticleDisplacements_x
tests/solutions/Test_L0/ParticleDisplacements_y
tests/solutions/Test_L0/ParticleDisplacements_z
tests/solutions/Test_L0/ParticleVelocities_x
tests/solutions/Test_L0/ParticleVelocities_y
tests/solutions/Test_L0/ParticleVelocities_z
tests/solutions/Test_L0/RunFinished
tests/solutions/Test_L0/Test_L0.conf
tests/solutions/Test_L0/Test_L0.enzo
tests/solutions/Test_L0/halo_0_region_point_file_L0
tests/solutions/Test_L0/parameter_file.txt
tests/solutions/Test_L0/RD0000/RD0000
tests/solutions/Test_L0/RD0000/RD0000.boundary
tests/solutions/Test_L0/RD0000/RD0000.configure
tests/solutions/Test_L0/RD0000/RD0000.cpu0000
tests/solutions/Test_L0/RD0000/RD0000.hierarchy
tests/solutions/Test_L0/RD0000/RD0000.memorymap
tests/solutions/Test_L0/RD0076/RD0076
tests/solutions/Test_L0/RD0076/RD0076.boundary
tests/solutions/Test_L0/RD0076/RD0076.configure
tests/solutions/Test_L0/RD0076/RD0076.cpu0000
tests/solutions/Test_L0/RD0076/RD0076.hierarchy
tests/solutions/Test_L0/RD0076/RD0076.memorymap
tests/solutions/Test_L1/ParticleDisplacements_x.0
tests/solutions/Test_L1/ParticleDisplacements_x.1
tests/solutions/Test_L1/ParticleDisplacements_y.0
tests/solutions/Test_L1/ParticleDisplacements_y.1
tests/solutions/Test_L1/ParticleDisplacements_z.0
