Metadata-Version: 2.1
Name: Zoomin
Version: 1.0.1
Summary: Automated generator of initial conditions for zoom-in cosmological simulations
Home-page: https://github.com/cjllorente827/Zoomin
Author: CJ Llorente
Author-email: llorente@msu.edu
License: GNU GPL 3.0
Keywords: cosmology simulation zoom
Platform: UNKNOWN
Classifier: Programming Language :: Python :: 3
Classifier: Programming Language :: Python :: 3.6
Classifier: Programming Language :: Python :: 3.7
Classifier: Programming Language :: Python :: 3.8
Classifier: Programming Language :: Python :: 3.9
Classifier: Programming Language :: Python :: 3.10
Classifier: Programming Language :: Python :: 3.11
Classifier: Programming Language :: Python :: 3.12
Requires-Python: >=3
License-File: LICENSE.txt
